tabletop/__init__.py
tabletop-0.0.1.dist-info/METADATA
tabletop-0.0.1.dist-info/WHEEL
tabletop-0.0.1.dist-info/top_level.txt
tabletop-0.0.1.dist-info/zip-safe
tabletop-0.0.1.dist-info/RECORD
